octostar_ai/__init__.py
octostar_ai/documents/__init__.py
octostar_ai/documents/commons.py
octostar_ai/documents/entities.py
octostar_ai/runnables/__init__.py
octostar_ai/runnables/embedders/__init__.py
octostar_ai/runnables/embedders/commons.py
octostar_ai/runnables/embedders/prefabs.py
octostar_ai/splitters/__init__.py
octostar_ai/splitters/commons.py
octostar_ai/splitters/entities.py
octostar_ai/splitters/postprocessors/__init__.py
octostar_ai/splitters/postprocessors/commons.py
octostar_ai/splitters/prefabs.py
octostar_ai/utils/__init__.py
octostar_ai/utils/gpu.py
octostar_ai/utils/vectors.py
octostar_ai-0.0.9.dist-info/LICENSE
octostar_ai-0.0.9.dist-info/METADATA
octostar_ai-0.0.9.dist-info/WHEEL
octostar_ai-0.0.9.dist-info/RECORD
